room_env/__init__.py
room_env/create_room_v2.py
room_env/create_room_v3.py
room_env/des.py
room_env/utils.py
room_env/data/conceptnet-data.json
room_env/data/des-config-l-v1.json
room_env/data/des-config-m-v1.json
room_env/data/des-config-s-v1.json
room_env/data/des-config-xs-v1.json
room_env/data/des-config-xxs-v1.json
room_env/data/human-locations
room_env/data/human-names
room_env/data/moving_objects.txt
room_env/data/ms-coco-80-categories
room_env/data/names-v2.json
room_env/data/room-config-dev-v2.json
room_env/data/room-config-dev-v3.json
room_env/data/room-config-l-different-prob-v2.json
room_env/data/room-config-l-v2.json
room_env/data/room-config-large-01-v3.json
room_env/data/room-config-large-02-q-v3.json
room_env/data/room-config-large-02-v3.json
room_env/data/room-config-large-03-v3.json
room_env/data/room-config-large-complex-v3.json
room_env/data/room-config-large-simple-v3.json
room_env/data/room-config-large-test-01-v3.json
room_env/data/room-config-large-test-02-v3.json
room_env/data/room-config-m-different-prob-v2.json
room_env/data/room-config-m-v2.json
room_env/data/room-config-medium-01-v3.json
room_env/data/room-config-medium-02-v3.json
room_env/data/room-config-medium-complex-v3.json
room_env/data/room-config-medium-simple-v3.json
room_env/data/room-config-medium-test-01-v3.json
room_env/data/room-config-medium-test-02-v3.json
room_env/data/room-config-period-test-v3.json
room_env/data/room-config-s-different-prob-v2.json
room_env/data/room-config-s-v2.json
room_env/data/room-config-small-01-v3.json
room_env/data/room-config-small-02-v3.json
room_env/data/room-config-small-complex-v3.json
room_env/data/room-config-small-simple-v3.json
room_env/data/room-config-small-test-01-v3.json
room_env/data/room-config-small-test-02-v3.json
room_env/data/room-config-test-v3.json
room_env/data/room-config-xl-different-prob-v2.json
room_env/data/room-config-xl-v2.json
room_env/data/room-config-xs-different-prob-v2.json
room_env/data/room-config-xs-v2.json
room_env-3.0.5.dist-info/LICENSE
room_env-3.0.5.dist-info/METADATA
room_env-3.0.5.dist-info/WHEEL
room_env-3.0.5.dist-info/top_level.txt
room_env-3.0.5.dist-info/RECORD
