Metadata-Version: 2.1
Name: room-env
Version: 3.0.5
Summary: The Room environment
Home-page: https://github.com/humemai/room-env
Author: Taewoon Kim
Author-email: info@humem.ai
Project-URL: Bug Tracker, https://github.com/humemai/room-env/issues
Classifier: Programming Language :: Python :: 3
Classifier: License :: OSI Approved :: MIT License
Classifier: Operating System :: OS Independent
Requires-Python: >=3.8
License-File: LICENSE
Requires-Dist: gymnasium<1,>=0.27.1
Requires-Dist: torch>=1.12.1
Requires-Dist: PyYAML>=6.0
Requires-Dist: networkx>=3.5
Requires-Dist: tqdm
Requires-Dist: matplotlib
Requires-Dist: Ipython
Requires-Dist: rdflib
